py_proj_init/__init__.py
py_proj_init/__main__.py
py_proj_init/data/.DS_Store
py_proj_init/data/templates/.DS_Store
py_proj_init/data/templates/.gitignore
py_proj_init/data/templates/LICENSE
py_proj_init/data/templates/MANIFEST.in
py_proj_init/data/templates/README.md
py_proj_init/data/templates/requirements.txt
py_proj_init/data/templates/setup.py
py_proj_init/data/templates/tests/test.py
py_proj_init/data/templates/{package_name}/__init__.py
py_proj_init/data/templates/{package_name}/__main__.py
py_proj_init/data/templates/{package_name}/data/.gitkeep
py_proj_init-1.0.0a0.dist-info/LICENSE
py_proj_init-1.0.0a0.dist-info/METADATA
py_proj_init-1.0.0a0.dist-info/WHEEL
py_proj_init-1.0.0a0.dist-info/entry_points.txt
py_proj_init-1.0.0a0.dist-info/top_level.txt
py_proj_init-1.0.0a0.dist-info/RECORD
