Metadata-Version: 2.1
Name: py-proj-init
Version: 1.0.0a0
Summary: Python3 project directory initializer
Home-page: https://github.com/ZhenningLang/py-proj-init
Author: ZhenningLang
Author-email: zhenninglang@163.com
License: UNKNOWN
Platform: UNKNOWN
Classifier: Programming Language :: Python :: 3
Classifier: License :: OSI Approved :: MIT License
Classifier: Operating System :: OS Independent
Requires-Python: >=3.2
